LICENSE
README.md
setup.py
file_manager_reichtangle/__init__.py
file_manager_reichtangle/file_manager_reichtangle.py
file_manager_reichtangle.egg-info/PKG-INFO
file_manager_reichtangle.egg-info/SOURCES.txt
file_manager_reichtangle.egg-info/dependency_links.txt
file_manager_reichtangle.egg-info/top_level.txt