Metadata-Version: 2.2
Name: file_manager_reichtangle
Version: 0.1
Summary: un tipo de gestor de archivos
Home-page: https://github.com/Mrreich/file_manager_reichtangle
Download-URL: https://github.com/nelsonher019/nelsonsaludo/tarball/0.1
Author: reichtangle
Author-email: mr.reich.oficial.1@gmail.com
License: MIT
Keywords: testing,logging,example
License-File: LICENSE
Dynamic: author
Dynamic: author-email
Dynamic: description
Dynamic: description-content-type
Dynamic: download-url
Dynamic: home-page
Dynamic: keywords
Dynamic: license
Dynamic: summary
